[
    {
        "flag": 0, 
        "gripper_width": 0.075, 
        "gripper_pose": {
            "position": {
                "y": -0.02090294594, 
                "x": 0.002319453601, 
                "z": 0.1038525194
            }, 
            "orientation": {
                "y": 0.5994639939, 
                "x": 0.5432783975, 
                "z": -0.3947148603, 
                "w": 0.4355360856
            }
        }
    }, 
    {
        "flag": 0, 
        "gripper_width": 0.075, 
        "gripper_pose": {
            "position": {
                "y": 0.002161544977, 
                "x": 4.591845354e-05, 
                "z": 0.1038525194
            }, 
            "orientation": {
                "y": 0.4355360856, 
                "x": 0.3947148603, 
                "z": -0.5432783975, 
                "w": 0.5994639939
            }
        }
    }, 
    {
        "flag": 0, 
        "gripper_width": 0.075, 
        "gripper_pose": {
            "position": {
                "y": 0.07929045231, 
                "x": -0.0001796944475, 
                "z": -0.0433923
            }, 
            "orientation": {
                "y": 0, 
                "x": 0, 
                "z": -0.6900142749, 
                "w": 0.7237957588
            }
        }
    }, 
    {
        "flag": 0, 
        "gripper_width": 0.075, 
        "gripper_pose": {
            "position": {
                "y": 0.08463543052, 
                "x": -0.005663049201, 
                "z": -0.0557901
            }, 
            "orientation": {
                "y": -0.6612850101, 
                "x": 0.7501347448, 
                "z": 4.593250571e-17, 
                "w": 4.049202855e-17
            }
        }
    }, 
    {
        "flag": 0, 
        "gripper_width": 0.075, 
        "gripper_pose": {
            "position": {
                "y": 0.07753010553, 
                "x": -0.00476492103, 
                "z": -0.03374815304
            }, 
            "orientation": {
                "y": -0.628919418, 
                "x": 0.7134205372, 
                "z": -0.2318043842, 
                "w": -0.2043483062
            }
        }
    }, 
    {
        "flag": 0, 
        "gripper_width": 0.075, 
        "gripper_pose": {
            "position": {
                "y": 0.07091970012, 
                "x": 0.004354024413, 
                "z": 0.0433923
            }, 
            "orientation": {
                "y": 0, 
                "x": 0, 
                "z": -0.7342002552, 
                "w": 0.6789329755
            }
        }
    }, 
    {
        "flag": 0, 
        "gripper_width": 0.075, 
        "gripper_pose": {
            "position": {
                "y": 0.06587470938, 
                "x": 0.001128699816, 
                "z": -0.0309945
            }, 
            "orientation": {
                "y": 0.7336407051, 
                "x": -0.679537575, 
                "z": -4.16096758e-17, 
                "w": -4.492253706e-17
            }
        }
    }, 
    {
        "flag": 0, 
        "gripper_width": 0.075, 
        "gripper_pose": {
            "position": {
                "y": 0.06847181033, 
                "x": -0.001381023077, 
                "z": 0.05822115404
            }, 
            "orientation": {
                "y": -0.706999813, 
                "x": 0.706999813, 
                "z": -0.01229896152, 
                "w": -0.01229896152
            }
        }
    }, 
    {
        "flag": 0, 
        "gripper_width": 0.075, 
        "gripper_pose": {
            "position": {
                "y": -0.06801474197, 
                "x": 0.001230959207, 
                "z": -0.01937112245
            }, 
            "orientation": {
                "y": 0.7048415518, 
                "x": 0.7048415518, 
                "z": 0.05655428248, 
                "w": -0.05655428248
            }
        }
    }, 
    {
        "flag": 0, 
        "gripper_width": 0.075, 
        "gripper_pose": {
            "position": {
                "y": -0.06584730747, 
                "x": -0.001360991169, 
                "z": -0.0061989
            }, 
            "orientation": {
                "y": 0.6791066081, 
                "x": 0.7340396548, 
                "z": 4.494696569e-17, 
                "w": -4.158328669e-17
            }
        }
    }, 
    {
        "flag": 0, 
        "gripper_width": 0.075, 
        "gripper_pose": {
            "position": {
                "y": -0.01474962115, 
                "x": 0.001286084515, 
                "z": 0.1019782737
            }, 
            "orientation": {
                "y": 0.5540801456, 
                "x": 0.5540801456, 
                "z": -0.4393121809, 
                "w": 0.4393121809
            }
        }
    }, 
    {
        "flag": 0, 
        "gripper_width": 0.075, 
        "gripper_pose": {
            "position": {
                "y": 0.06801294883, 
                "x": 0.001348545833, 
                "z": -0.0061989
            }, 
            "orientation": {
                "y": 0, 
                "x": 0, 
                "z": -0.701954201, 
                "w": 0.712222086
            }
        }
    }, 
    {
        "flag": 0, 
        "gripper_width": 0.075, 
        "gripper_pose": {
            "position": {
                "y": -0.06398005013, 
                "x": -0.003591479631, 
                "z": -0.0681879
            }, 
            "orientation": {
                "y": 0.6598618608, 
                "x": 0.751386934, 
                "z": 4.600918018e-17, 
                "w": -4.040488579e-17
            }
        }
    }
]