[
    {
        "flag": 0, 
        "gripper_width": 0.075, 
        "gripper_pose": {
            "position": {
                "y": 0.01565940928, 
                "x": -0.0002721538625, 
                "z": 0.09344815039
            }, 
            "orientation": {
                "y": -0.5666297102, 
                "x": 0.5666297102, 
                "z": -0.4230020939, 
                "w": -0.4230020939
            }
        }
    }, 
    {
        "flag": 0, 
        "gripper_width": 0.075, 
        "gripper_pose": {
            "position": {
                "y": 0.004027616513, 
                "x": -0.0002721538625, 
                "z": 0.0949827334
            }, 
            "orientation": {
                "y": 0.493481452, 
                "x": -0.493481452, 
                "z": 0.5064346518, 
                "w": 0.5064346518
            }
        }
    }, 
    {
        "flag": 0, 
        "gripper_width": 0.075, 
        "gripper_pose": {
            "position": {
                "y": -0.00750908802, 
                "x": -0.0002721538625, 
                "z": 0.09284778693
            }, 
            "orientation": {
                "y": 0.4081820426, 
                "x": -0.4081820426, 
                "z": 0.5773971078, 
                "w": 0.5773971078
            }
        }
    }, 
    {
        "flag": 0, 
        "gripper_width": 0.075, 
        "gripper_pose": {
            "position": {
                "y": -0.0178214113, 
                "x": -0.0002721538625, 
                "z": 0.08725229441
            }, 
            "orientation": {
                "y": 0.3128318366, 
                "x": -0.3128318366, 
                "z": 0.6341421308, 
                "w": 0.6341421308
            }
        }
    }, 
    {
        "flag": 0, 
        "gripper_width": 0.075, 
        "gripper_pose": {
            "position": {
                "y": -0.02113883089, 
                "x": -0.003084210652, 
                "z": -0.09358388342
            }, 
            "orientation": {
                "y": -0.3773609599, 
                "x": 0.3773609599, 
                "z": 0.5979955735, 
                "w": 0.5979955735
            }
        }
    }, 
    {
        "flag": 0, 
        "gripper_width": 0.075, 
        "gripper_pose": {
            "position": {
                "y": -0.009888967805, 
                "x": -0.003084210652, 
                "z": -0.09691466839
            }, 
            "orientation": {
                "y": -0.466262138, 
                "x": 0.466262138, 
                "z": 0.5316009958, 
                "w": 0.5316009958
            }
        }
    }, 
    {
        "flag": 0, 
        "gripper_width": 0.075, 
        "gripper_pose": {
            "position": {
                "y": 0.001839556948, 
                "x": -0.003084210652, 
                "z": -0.09660603427
            }, 
            "orientation": {
                "y": -0.5436823947, 
                "x": 0.5436823947, 
                "z": 0.4521166372, 
                "w": 0.4521166372
            }
        }
    }, 
    {
        "flag": 0, 
        "gripper_width": 0.075, 
        "gripper_pose": {
            "position": {
                "y": 0.01289867365, 
                "x": -0.003084210652, 
                "z": -0.09268819231
            }, 
            "orientation": {
                "y": -0.6077153865, 
                "x": 0.6077153865, 
                "z": 0.3614996666, 
                "w": 0.3614996666
            }
        }
    }, 
    {
        "flag": 0, 
        "gripper_width": 0.075, 
        "gripper_pose": {
            "position": {
                "y": -0.009860308904, 
                "x": -0.0006601246812, 
                "z": 0.08992400412
            }, 
            "orientation": {
                "y": 0.590814883, 
                "x": 0.590814883, 
                "z": -0.3885071093, 
                "w": 0.3885071093
            }
        }
    }, 
    {
        "flag": 0, 
        "gripper_width": 0.075, 
        "gripper_pose": {
            "position": {
                "y": 0.001506527296, 
                "x": -0.0006601246812, 
                "z": 0.0928306487
            }, 
            "orientation": {
                "y": 0.5227650696, 
                "x": 0.5227650696, 
                "z": -0.4761477523, 
                "w": 0.4761477523
            }
        }
    }, 
    {
        "flag": 0, 
        "gripper_width": 0.075, 
        "gripper_pose": {
            "position": {
                "y": 0.01321523351, 
                "x": -0.0006601246812, 
                "z": 0.09208248641
            }, 
            "orientation": {
                "y": 0.4418430452, 
                "x": 0.4418430452, 
                "z": -0.5520640573, 
                "w": 0.5520640573
            }
        }
    }, 
    {
        "flag": 0, 
        "gripper_width": 0.075, 
        "gripper_pose": {
            "position": {
                "y": 0.005080640437, 
                "x": -0.0009594364284, 
                "z": 0.082491225
            }, 
            "orientation": {
                "y": -0.4992132472, 
                "x": 0.5007855168, 
                "z": -0.5007855168, 
                "w": -0.4992132472
            }
        }
    }, 
    {
        "flag": 0, 
        "gripper_width": 0.075, 
        "gripper_pose": {
            "position": {
                "y": -0.006507439559, 
                "x": -0.0009229971219, 
                "z": 0.08065584436
            }, 
            "orientation": {
                "y": 0.4149729465, 
                "x": -0.4162799016, 
                "z": 0.5729601305, 
                "w": 0.571161261
            }
        }
    }
]